{
"type": "FeatureCollection",
"name": "geo_37_介護医療院",
"crs": { "type": "name", "properties": { "name": "urn:ogc:def:crs:OGC:1.3:CRS84" } },
"features": [
{ "type": "Feature", "properties": { "内容": "伊達病院　介護医療院【介護医療院】香川県高松市観光町588－8", "url": "https://www.kaigokensaku.mhlw.go.jp/37/index.php?action_kouhyou_detail_004_kani=true&JigyosyoCd=37B0100027-00&ServiceCd=550&Type=search", "url2": "https://date-med.or.jp/" }, "geometry": { "type": "Point", "coordinates": [ 134.0609986, 34.3339891 ] } },
{ "type": "Feature", "properties": { "内容": "介護医療院　やわらぎ【介護医療院】香川県高松市香南町由佐102-1", "url": "https://www.kaigokensaku.mhlw.go.jp/37/index.php?action_kouhyou_detail_004_kani=true&JigyosyoCd=37B0100019-00&ServiceCd=550&Type=search", "url2": "http://www.iwaki-hospital.or.jp/yawaragi/" }, "geometry": { "type": "Point", "coordinates": [ 134.0215571, 34.236402 ] } },
{ "type": "Feature", "properties": { "内容": "医療法人社団光風会介護医療院　コリーナ【介護医療院】高松市牟礼町原943-1", "url": "https://www.kaigokensaku.mhlw.go.jp/37/index.php?action_kouhyou_detail_004_kani=true&JigyosyoCd=37B0100043-00&ServiceCd=550&Type=search", "url2": null }, "geometry": { "type": "Point", "coordinates": [ 134.150257, 34.3310215 ] } },
{ "type": "Feature", "properties": { "内容": "介護医療院千手苑【介護医療院】香川県善通寺市原田町1486番地3", "url": "https://www.kaigokensaku.mhlw.go.jp/37/index.php?action_kouhyou_detail_004_kani=true&JigyosyoCd=37B0400013-00&ServiceCd=550&Type=search", "url2": "http://www.senju-group.or.jp" }, "geometry": { "type": "Point", "coordinates": [ 133.787631299999987, 34.2537342 ] } },
{ "type": "Feature", "properties": { "内容": "松井病院介護医療院【介護医療院】香川県観音寺市村黒町739番地", "url": "https://www.kaigokensaku.mhlw.go.jp/37/index.php?action_kouhyou_detail_004_kani=true&JigyosyoCd=37B0500010-00&ServiceCd=550&Type=search", "url2": "http://www.matsui-hp.com" }, "geometry": { "type": "Point", "coordinates": [ 133.666388899999987, 34.1339 ] } },
{ "type": "Feature", "properties": { "内容": "医療法人日昭会　岡病院　介護医療院【介護医療院】香川県さぬき市志度1562番地", "url": "https://www.kaigokensaku.mhlw.go.jp/37/index.php?action_kouhyou_detail_004_kani=true&JigyosyoCd=37B0600018-00&ServiceCd=550&Type=search", "url2": "https://sanuki-oka-hosp.sakura.ne.jp/kaigoiryouin/" }, "geometry": { "type": "Point", "coordinates": [ 134.1951402, 34.3202271 ] } },
{ "type": "Feature", "properties": { "内容": "医療法人社団聖心会　阪本病院　介護医療院【介護医療院】香川県東かがわ市川東103番地1", "url": "https://www.kaigokensaku.mhlw.go.jp/37/index.php?action_kouhyou_detail_004_kani=true&JigyosyoCd=37B0700016-00&ServiceCd=550&Type=search", "url2": "https://www.sakamoto-hosp.or.jp/sakamoto/htm/" }, "geometry": { "type": "Point", "coordinates": [ 139.5029661, 35.7745398 ] } },
{ "type": "Feature", "properties": { "内容": "小豆島病院介護医療院【介護医療院】香川県小豆郡小豆島町池田２５１９－４", "url": "https://www.kaigokensaku.mhlw.go.jp/37/index.php?action_kouhyou_detail_004_kani=true&JigyosyoCd=37B1200016-00&ServiceCd=550&Type=search", "url2": "https://www.syodoshima-hp.jp/main/iryouin.html" }, "geometry": { "type": "Point", "coordinates": [ 134.230887526983651, 34.484465663693456 ] } },
{ "type": "Feature", "properties": { "内容": "直島町立診療所介護医療院【介護医療院】２３１０－１", "url": "https://www.kaigokensaku.mhlw.go.jp/37/index.php?action_kouhyou_detail_004_kani=true&JigyosyoCd=3717011344-00&ServiceCd=550&Type=search", "url2": "https://www.town.naoshima.lg.jp/" }, "geometry": { "type": "Point", "coordinates": [ -52.769563, 47.432371 ] } },
{ "type": "Feature", "properties": { "内容": "直島町立診療所介護医療院【介護医療院】香川県香川郡直島町2310番地1", "url": "https://www.kaigokensaku.mhlw.go.jp/37/index.php?action_kouhyou_detail_004_kani=true&JigyosyoCd=37B1400012-00&ServiceCd=550&Type=search", "url2": "https://naoshimacho.kir.jp/oshirase/kyukyu/post_6.html" }, "geometry": { "type": "Point", "coordinates": [ 133.974172718654415, 34.460369174858272 ] } },
{ "type": "Feature", "properties": { "内容": "おおにし介護医療院【介護医療院】香川県仲多度郡琴平町350－10", "url": "https://www.kaigokensaku.mhlw.go.jp/37/index.php?action_kouhyou_detail_004_kani=true&JigyosyoCd=37B1600025-00&ServiceCd=550&Type=search", "url2": "https://keisyokai.com" }, "geometry": { "type": "Point", "coordinates": [ 133.819253300000014, 34.1927724 ] } },
{ "type": "Feature", "properties": { "内容": "医療法人社団　小国医院　介護医療院【介護医療院】香川県仲多度郡まんのう町四條７７７", "url": "https://www.kaigokensaku.mhlw.go.jp/37/index.php?action_kouhyou_detail_004_kani=true&JigyosyoCd=37B1600033-00&ServiceCd=550&Type=search", "url2": "http://www.oguni.or.jp" }, "geometry": { "type": "Point", "coordinates": [ 133.8369007, 34.1950557 ] } },
{ "type": "Feature", "properties": { "内容": "医療法人圭良会　永生病院介護医療院【介護医療院】香川県仲多度郡まんのう町買田221-3永生病院", "url": "https://www.kaigokensaku.mhlw.go.jp/37/index.php?action_kouhyou_detail_004_kani=true&JigyosyoCd=37B1600017-00&ServiceCd=550&Type=search", "url2": "http://www.eisei-hp.or.jp/" }, "geometry": { "type": "Point", "coordinates": [ 133.827381, 34.1721428 ] } }
]
}
